data_file_profiler_utils/__init__.py
data_file_profiler_utils/console_helper.py
data_file_profiler_utils/constants.py
data_file_profiler_utils/data_file_profiler_utils.py
data_file_profiler_utils/manager.py
data_file_profiler_utils-0.1.0.dist-info/AUTHORS.rst
data_file_profiler_utils-0.1.0.dist-info/METADATA
data_file_profiler_utils-0.1.0.dist-info/WHEEL
data_file_profiler_utils-0.1.0.dist-info/entry_points.txt
data_file_profiler_utils-0.1.0.dist-info/top_level.txt
data_file_profiler_utils-0.1.0.dist-info/RECORD
